bharatocrclient/__init__.py
bharatocrclient/clients/__init__.py
bharatocrclient/clients/aadhaar.py
bharatocrclient/clients/api.py
bharatocrclient/clients/auth.py
bharatocrclient/clients/birth_certificate.py
bharatocrclient/clients/common.py
bharatocrclient/clients/degree.py
bharatocrclient/clients/driving_licence.py
bharatocrclient/clients/exceptions.py
bharatocrclient/clients/pan.py
bharatocrclient/clients/passport.py
bharatocrclient/clients/vehicle_registration.py
bharatocrclient/clients/voter_id.py
bharatocrclient/clients/water_bill.py
bharatocr_client-0.4.1.dist-info/LICENSE
bharatocr_client-0.4.1.dist-info/METADATA
bharatocr_client-0.4.1.dist-info/WHEEL
bharatocr_client-0.4.1.dist-info/top_level.txt
bharatocr_client-0.4.1.dist-info/RECORD
