Metadata-Version: 2.1
Name: bharatocr-client
Version: 0.4.1
Summary: bharatocr-client is an opensource python library to access BharatOcrAPIs 
Home-page: https://github.com/essentiasoftserv/bharatocrclient
Author: essentiasoftserv
Author-email: kunal@essentia.dev
License: Apache
Requires-Python: >=3.6
License-File: LICENSE
